bot_engine/bot/Bot.py
bot_engine/bot/Filters.py
bot_engine/data/config.py
bot_engine/data/env.py
bot_engine/database/Cache.py
bot_engine/database/Database.py
bot_engine/database/MongoDB.py
bot_engine/dialogs/BotDialogs.py
bot_engine/dialogs/DialogGenerator.py
bot_engine/dialogs/InlineKeyboard.py
bot_engine/languages/Languages.py
bot_engine/languages/Locale.py
bot_engine/main.py
bot_engine/server/FastAPIServer.py
bot_engine/templates/BotDialogs.py
bot_engine/templates/DialogsExample.py
bot_engine/templates/initial_users.py
bot_engine/users/InitialUsers.py
bot_engine/users/NewUser.py
bot_engine/users/UserT.py
bot_engine/utils/Dotenv.py
bot_engine/utils/Logger.py
bot_engine/utils/Path.py
bot_engine/utils/Schedule.py
bot_engine-0.2.5.dist-info/LICENSE
bot_engine-0.2.5.dist-info/METADATA
bot_engine-0.2.5.dist-info/WHEEL
bot_engine-0.2.5.dist-info/RECORD
